snappy_manifolds/__init__.py
snappy_manifolds/database.py
snappy_manifolds/test.py
snappy_manifolds/sqlite_files/__init__.py
snappy_manifolds/sqlite_files/make_sqlite_db.py
snappy_manifolds/sqlite_files/manifolds.sqlite
snappy_manifolds/sqlite_files/more_manifolds.sqlite
snappy_manifolds/sqlite_files/platonic_manifolds.sqlite
snappy_manifolds-1.2.1.dist-info/METADATA
snappy_manifolds-1.2.1.dist-info/WHEEL
snappy_manifolds-1.2.1.dist-info/top_level.txt
snappy_manifolds-1.2.1.dist-info/RECORD
