Metadata-Version: 2.1
Name: snappy_manifolds
Version: 1.2.1
Summary: Database of snappy manifolds
Author: Malik Obeidin
Author-email: Marc Culler <snappy-help@computop.org>, "Nathan M. Dunfield" <snappy-help@computop.org>, Matthias Goerner <snappy-help@computop.org>
License: GPLv2+
Project-URL: Homepage, https://github.com/3-manifolds/snappy_manifolds
Classifier: Development Status :: 5 - Production/Stable
Classifier: Intended Audience :: Science/Research
Classifier: License :: OSI Approved :: GNU General Public License v2 or later (GPLv2+)
Classifier: Operating System :: OS Independent
Classifier: Programming Language :: C
Classifier: Programming Language :: Cython
Classifier: Programming Language :: Python
Classifier: Topic :: Scientific/Engineering :: Mathematics
